glue_utils/__init__.py
glue_utils/helpers.py
glue_utils/options.py
glue_utils/py.typed
glue_utils/pyspark/__init__.py
glue_utils/pyspark/connection_options.py
glue_utils/pyspark/connection_types.py
glue_utils/pyspark/format_options.py
glue_utils/pyspark/formats.py
glue_utils/pyspark/job.py
glue_utils/pyspark/context/__init__.py
glue_utils/pyspark/context/documentdb.py
glue_utils/pyspark/context/dynamodb.py
glue_utils/pyspark/context/jdbc.py
glue_utils/pyspark/context/kafka.py
glue_utils/pyspark/context/kinesis.py
glue_utils/pyspark/context/mongodb.py
glue_utils/pyspark/context/opensearch.py
glue_utils/pyspark/context/s3.py
glue_utils-0.12.0.dist-info/METADATA
glue_utils-0.12.0.dist-info/WHEEL
glue_utils-0.12.0.dist-info/licenses/LICENSE
glue_utils-0.12.0.dist-info/RECORD
