Metadata-Version: 2.4
Name: glue-utils
Version: 0.12.0
Summary: Reusable utilities for working with Glue PySpark jobs
Project-URL: homepage, https://github.com/dashmug/glue-utils
Project-URL: repository, https://github.com/dashmug/glue-utils/issues
Project-URL: documentation, https://github.com/dashmug/glue-utils/wiki
Author-email: Noel Llevares <dashmug@gmail.com>
License-Expression: MIT
License-File: LICENSE
Keywords: aws,data,data-engineering,etl,glue,pyspark,spark
Classifier: Development Status :: 4 - Beta
Classifier: Intended Audience :: Developers
Classifier: License :: OSI Approved :: MIT License
Classifier: Natural Language :: English
Classifier: Operating System :: OS Independent
Classifier: Programming Language :: Python :: 3.9
Classifier: Programming Language :: Python :: 3.10
Classifier: Programming Language :: Python :: 3.11
Classifier: Topic :: Software Development :: Libraries
Classifier: Topic :: Software Development :: Libraries :: Python Modules
Classifier: Typing :: Typed
Requires-Python: >=3.9
